<DOMSymbolItem xmlns:xsi="http://www.w3.org/2001/XMLSchema-instance" xmlns="http://ns.adobe.com/xfl/2008/" name="Symbol 9" itemID="53f8df77-00000338" lastModified="1408819063">
  <timeline>
    <DOMTimeline name="Symbol 9">
      <layers>
        <DOMLayer name="Layer 1" color="#4FFF4F" current="true" isSelected="true">
          <frames>
            <DOMFrame index="0" keyMode="9728">
              <elements>
                <DOMShape>
                  <fills>
                    <FillStyle index="1">
                      <SolidColor color="#DDDCDC"/>
                    </FillStyle>
                    <FillStyle index="2">
                      <SolidColor color="#333333"/>
                    </FillStyle>
                    <FillStyle index="3">
                      <SolidColor color="#FFFFFF"/>
                    </FillStyle>
                  </fills>
                  <edges>
                    <Edge fillStyle1="2" edges="!64 602S2[43 623 7 593!7 593[10 585 12 581!12 581[16 569 17 562!17 562[18 554 19 546!19 546[7 578 0 589!0 589[-2 564 6 529!6 529[13 498 28 475!28 475[31 446 35 421!35 421[36 406 37 388!37 388[38 336 51 302!51 302|50 300!50 300[39 266
 67 171!67 171[87 101 100 79!100 79[100 78 99 76!99 76[94 60 141 50!141 50[134 51 126 52!126 52|105 42!105 42[103 35 104 35!104 35[105 32 105 30!105 30[357 -10 435 4!435 4[502 16 526 94!526 94[542 147 527 250!527 250[527 286 524 335!524
 335[512 472 514 487!514 487[519 572 512 636!512 636[458 671 442 633"/>
                    <Edge fillStyle1="3" edges="
!442 633S2[311 641 250 623!250 623[243 615 153 615!153 615[73 615 64 602"/>
                    <Edge fillStyle0="1" fillStyle1="2" edges="
!467 391S3[475 357 481 330!481 330[480 324 482 320!482 320[482 304 482 290!482 290[484 262 486 238!486 238[492 169 501 154!501 154[500 125 493 105!493 105[476 48 401 37!401 37[341 28 220 40!220 40[261 39 304 43!304 43[304 48 303 51!303
 51[303 54 294 57!294 57[287 59 270 59!270 59[265 57 259 57!259 57[235 53 234 53!234 53[163 74 131 81"/>
                    <Edge fillStyle0="1" edges="
!131 81S1[123 86 118 92"/>
                    <Edge fillStyle0="1" fillStyle1="2" edges="
!118 92S3[120 97 121 100!121 100[122 129 124 154!124 154[124 157 124 160!124 160[129 306 88 322!88 322[88 336 83 381!83 381|83 382!83 382[81 390 81 399!81 399[81 400 81 401"/>
                    <Edge fillStyle0="1" fillStyle1="3" edges="
!81 401S3[100 414 138 428!138 428[237 464 377 420!377 420[396 414 413 403!413 403[428 401 454 389!454 389[457 388 467 390!467 390|467 391"/>
                    <Edge fillStyle0="3" fillStyle1="2" edges="
!442 633S3[442 624 443 620!443 620[446 612 448 600!448 600[449 590 451 577!451 577[451 558 451 534!451 534[450 471 454 450!454 450[461 418 467 391"/>
                    <Edge fillStyle1="2" edges="
!131 81S2[119 84 112 84!112 84[115 88 118 92"/>
                    <Edge fillStyle0="2" edges="
!67 574S1|66 570!66 570|67 570!67 570[68 570 69 570"/>
                    <Edge fillStyle0="2" fillStyle1="3" edges="
!69 570S3[69 540 69 531!69 531[71 495 81 401"/>
                    <Edge fillStyle0="3" edges="
!69 570S1[68 572 67 574"/>
                    <Edge fillStyle0="3" fillStyle1="2" edges="
!67 574S3[61 584 62 598!62 598[62 600 64 602"/>
                    <Edge cubics="!514 487(;516,516 520,576 512,636q514 487Q519 572q512 636);"/>
                    <Edge cubics="!304 43(;301,49 307,53 294,57q304 43Q304 48q303 51Q303 54q294 57);"/>
                    <Edge cubics="!126 52(;111,45 106,43 105,42q126 52 105 42);"/>
                    <Edge cubics="!105 42(;102,30 104,38 105,30q105 42Q103 35q104 35Q105 32q105 30);"/>
                    <Edge cubics="!105 30(;452,-25 495,-7 526,94q105 30Q357 -10q435 4Q502 16q526 94);"/>
                    <Edge cubics="!17 562(;18,556 18,552 19,546q17 562Q18 554q19 546);"/>
                    <Edge cubics="!19 546(;10,567 5,582 0,589q19 546Q7 578q0 589);"/>
                    <Edge cubics="!0 589(;-2,572 1,552 6,529q0 589Q-2 564q6 529);"/>
                    <Edge cubics="!486 238(;491,192 495,164 501,154q486 238Q492 169q501 154);"/>
                    <Edge cubics="!526 94(;537,129 537,181 527,250q526 94Q542 147q527 250);"/>
                    <Edge cubics="!493 105(;482,67 450,44 401,37q493 105Q476 48q401 37);"/>
                    <Edge cubics="!501 154(;500,135 498,119 493,105q501 154Q500 125q493 105);"/>
                    <Edge cubics="!141 50(;136,50 131,51 126,52q141 50Q134 51q126 52);"/>
                    <Edge cubics="!99 76(;96,65 110,57 141,50q99 76Q94 60q141 50);"/>
                    <Edge cubics="!100 79(;100,78 100,77 99,76q100 79Q100 78q99 76);"/>
                    <Edge cubics="!51 302(;51,302 50,300 50,300q51 302 50 300);"/>
                    <Edge cubics="!35 421(;36,411 36,400 37,388q35 421Q36 406q37 388);"/>
                    <Edge cubics="!37 388(;37,354 42,325 51,302q37 388Q38 336q51 302);"/>
                    <Edge cubics="!67 171(;80,125 92,94 100,79q67 171Q87 101q100 79);"/>
                    <Edge cubics="!50 300(;43,277 49,234 67,171q50 300Q39 266q67 171);"/>
                    <Edge cubics="!451 534(;450,492 452,464 454,450q451 534Q450 471q454 450);"/>
                    <Edge cubics="!443 620(;444,614 446,608 448,600q443 620Q446 612q448 600);"/>
                    <Edge cubics="!448 600(;448,593 449,586 451,577q448 600Q449 590q451 577);"/>
                    <Edge cubics="!451 577(;451,565 451,550 451,534q451 577Q451 558q451 534);"/>
                    <Edge cubics="!524 335(;516,426 513,476 514,487q524 335Q512 472q514 487);"/>
                    <Edge cubics="!527 250(;527,274 526,303 524,335q527 250Q527 286q524 335);"/>
                    <Edge cubics="!28 475(;30,456 33,438 35,421q28 475Q31 446q35 421);"/>
                    <Edge cubics="!6 529(;10,508 18,490 28,475q6 529Q13 498q28 475);"/>
                    <Edge cubics="!294 57(;290,58 282,58 270,59q294 57Q287 59q270 59);"/>
                    <Edge cubics="!270 59(;267,58 263,58 259,57q270 59Q265 57q259 57);"/>
                    <Edge cubics="!482 320(;482,309 482,300 482,290q482 320Q482 304q482 290);"/>
                    <Edge cubics="!482 290(;483,271 485,254 486,238q482 290Q484 262q486 238);"/>
                    <Edge cubics="!112 84(;114,87 116,89 118,92q112 84Q115 88q118 92);"/>
                    <Edge cubics="!118 92(;119,95 120,98 121,100q118 92Q120 97q121 100);"/>
                    <Edge cubics="!131 81(;123,83 116,84 112,84q131 81Q119 84q112 84);"/>
                    <Edge cubics="!118 92(;122,89 126,85 131,81q118 92Q123 86q131 81);"/>
                    <Edge cubics="!124 154(;124,156 125,158 124,160q124 154Q124 157q124 160);"/>
                    <Edge cubics="!121 100(;123,120 124,137 124,154q121 100Q122 129q124 154);"/>
                    <Edge cubics="!234 53(;186,66 152,77 131,81q234 53Q163 74q131 81);"/>
                    <Edge cubics="!138 428(;113,419 94,410 81,401q138 428Q100 414q81 401);"/>
                    <Edge cubics="!88 322(;87,332 86,351 83,381q88 322Q88 336q83 381);"/>
                    <Edge cubics="!83 382(;82,388 81,393 81,399q83 382Q81 390q81 399);"/>
                    <Edge cubics="!83 381(;83,381 83,382 83,382q83 381 83 382);"/>
                    <Edge cubics="!81 399(;81,400 81,400 81,401q81 399Q81 400q81 401);"/>
                    <Edge cubics="!124 160(;127,257 115,311 88,322q124 160Q129 306q88 322);"/>
                    <Edge cubics="!467 391(;467,391 467,390 467,390q467 391 467 390);"/>
                    <Edge cubics="!467 391(;473,368 476,349 481,330q467 391Q475 357q481 330);"/>
                    <Edge cubics="!467 390(;460,388 456,388 454,389q467 390Q457 388q454 389);"/>
                    <Edge cubics="!413 403(;402,411 390,416 377,420q413 403Q396 414q377 420);"/>
                    <Edge cubics="!454 450(;459,428 463,409 467,391q454 450Q461 418q467 391);"/>
                    <Edge cubics="!454 389(;437,397 423,403 413,403q454 389Q428 401q413 403);"/>
                    <Edge cubics="!259 57(;243,55 235,53 234,53q259 57Q235 53q234 53);"/>
                    <Edge cubics="!81 401(;75,463 70,507 69,531q81 401Q71 495q69 531);"/>
                    <Edge cubics="!481 330(;479,327 481,323 482,320q481 330Q480 324q482 320);"/>
                    <Edge cubics="!377 420(;284,449 204,452 138,428q377 420Q237 464q138 428);"/>
                    <Edge cubics="!220 40(;247,39 275,40 304,43q220 40Q261 39q304 43);"/>
                    <Edge cubics="!401 37(;361,31 301,32 220,40q401 37Q341 28q220 40);"/>
                    <Edge cubics="!66 570(;66,570 67,570 67,570q66 570 67 570);"/>
                    <Edge cubics="!7 593(;9,588 11,584 12,581q7 593Q10 585q12 581);"/>
                    <Edge cubics="!12 581(;15,573 16,567 17,562q12 581Q16 569q17 562);"/>
                    <Edge cubics="!442 633(;442,627 442,623 443,620q442 633Q442 624q443 620);"/>
                    <Edge cubics="!67 570(;68,570 68,570 69,570q67 570Q68 570q69 570);"/>
                    <Edge cubics="!69 531(;69,537 69,550 69,570q69 531Q69 540q69 570);"/>
                    <Edge cubics="!67 574(;67,574 66,570 66,570q67 574 66 570);"/>
                    <Edge cubics="!69 570(;68,571 68,573 67,574q69 570Q68 572q67 574);"/>
                    <Edge cubics="!62 598(;62,599 63,601 64,602q62 598Q62 600q64 602);"/>
                    <Edge cubics="!67 574(;63,581 61,589 62,598q67 574Q61 584q62 598);"/>
                    <Edge cubics="!64 602(;50,616 31,613 7,593q64 602Q43 623q7 593);"/>
                    <Edge cubics="!153 615(;213,615 245,618 250,623q153 615Q243 615q250 623);"/>
                    <Edge cubics="!250 623(;291,635 355,638 442,633q250 623Q311 641q442 633);"/>
                    <Edge cubics="!442 633(;453,658 476,659 512,636q442 633Q458 671q512 636);"/>
                    <Edge cubics="!64 602(;70,611 100,615 153,615q64 602Q73 615q153 615);"/>
                  </edges>
                </DOMShape>
              </elements>
            </DOMFrame>
          </frames>
        </DOMLayer>
      </layers>
    </DOMTimeline>
  </timeline>
</DOMSymbolItem>