<DOMSymbolItem xmlns:xsi="http://www.w3.org/2001/XMLSchema-instance" xmlns="http://ns.adobe.com/xfl/2008/" name="leg" itemID="54cc4c8f-000003a9" lastModified="1423348144">
  <timeline>
    <DOMTimeline name="leg">
      <layers>
        <DOMLayer name="Layer 1" color="#4FFF4F" current="true" isSelected="true">
          <frames>
            <DOMFrame index="0" keyMode="9728">
              <elements>
                <DOMShape>
                  <fills>
                    <FillStyle index="1">
                      <SolidColor color="#ECECEC"/>
                    </FillStyle>
                    <FillStyle index="2">
                      <SolidColor color="#D79B39"/>
                    </FillStyle>
                    <FillStyle index="3">
                      <SolidColor color="#E2A349"/>
                    </FillStyle>
                  </fills>
                  <edges>
                    <Edge fillStyle0="2" edges="!189 1265[179 1269 161 1269!161 1269[63 1269 -17 1225!-17 1225[-52 1205 -81 1179!-81 1179[-76 1242 -51 1268!-51 1268[-54 1287 -54 1312!-54 1312[-84 1360 -80 1481!-80 1481|-80 1483!-80 1483|-81 1481!-81 1481[-84 1479 -86 1476!-86 1476
[-116 1431 -111 1502!-111 1502[-108 1537 -60 1651!-60 1651[-82 1678 -77 1714!-77 1714[-78 1729 -53 1774!-53 1774[-63 1800 -58 1840!-58 1840[-53 1916 -52 1950!-52 1950[-66 1970 -70 2056!-70 2056[-74 2084 -71 2109!-71 2109[-74 2103 -76
 2098!-76 2098[-79 2098 -84 2100!-84 2100[-88 2103 -87 2112!-87 2112[-8 2491 -6 2513!-6 2513|-7 2514!-7 2514[-7 2517 -7 2534!-7 2534[-9 2520 -10 2512!-10 2512[-19 2470 -31 2528!-31 2528[-48 2612 -44 2658!-44 2658[-42 2696 -11 2813!-11
 2813[-8 2826 -5 2838!-5 2838[-17 2845 -15 2864!-15 2864[-13 2874 3 2973!3 2973[-1 2979 -6 2989!-6 2989[-22 3017 -20 3025!-20 3025[-19 3033 -15 3037!-15 3037[-9 3049 11 3046!11 3046|12 3046!12 3046[14 3093 21 3231!21 3231[30 3334 42 3383
!42 3383|41 3384!41 3384[32 3388 35 3410!35 3410[33 3409 50 3498!50 3498[30 3495 31 3514!31 3514[31 3519 33 3522!33 3522[38 3550 69 3574!69 3574[89 3623 120 3620!120 3620[132 3639 138 3658!138 3658[146 3679 153 3697!153 3697[163 3722
 172 3741!172 3741[172 3744 172 3751!172 3751|204 3826!204 3826[231 3874 258 3888!258 3888[258 3890 258 3892!258 3892[257 3897 260 3903!260 3903[267 3909 281 3908!281 3908[315 3903 332 3857!332 3857[334 3848 337 3840!337 3840[337 3835
 337 3832!337 3832[340 3834 341 3836!341 3836[350 3848 361 3861!361 3861[415 3925 454 3920!454 3920[470 3917 481 3903!481 3903[487 3885 493 3880!493 3880|496 3881!496 3881[497 3890 505 3898!505 3898[515 3911 531 3910!531 3910[558 3906
 567 3882!567 3882[568 3876 567 3855!567 3855[567 3846 568 3846!568 3846[568 3845 575 3845!575 3845[583 3851 598 3849!598 3849[610 3848 625 3829!625 3829[630 3837 637 3848!637 3848[#281.AB #F0B.E4 656 3851!656 3851[#294.1E #F0A.AA 665
 3850!665 3850[680 3849 687 3837!687 3837[688 3834 689 3831!689 3831[695 3836 709 3838!709 3838[725 3843 752 3840!752 3840[757 3838 772 3833!772 3833[792 3826 797 3826!797 3826[802 3825 841 3860!841 3860[881 3892 903 3890!903 3890[905
 3889 910 3888!910 3888[923 3885 936 3872!936 3872[943 3878 955 3877!955 3877[958 3875 963 3875!963 3875[980 3870 994 3859!994 3859[1016 3835 1024 3831!1024 3831|1029 3841!1029 3841[1035 3851 1051 3848!1051 3848[1075 3844 1076 3817!1076
 3817|1077 3815!1077 3815|1088 3811!1088 3811[1091 3820 1109 3817!1109 3817[1137 3814 1191 3697!1191 3697[1216 3643 1248 3565!1248 3565[1248 3544 1245 3541!1245 3541[1261 3500 1283 3436!1283 3436[1306 3404 1330 3344!1330 3344|1367 3216
!1367 3216[1368 3195 1356 3198!1356 3198[1362 3186 1368 3170!1368 3170[1389 3119 1395 3100!1395 3100[1411 3090 1423 3068!1423 3068[1438 3040 1440 3027!1440 3027[1440 3015 1439 3008!1439 3008[1446 2987 1454 2959!1454 2959[1479 2878 1482
 2856!1482 2856[1483 2812 1481 2799!1481 2799[1496 2768 1510 2709!1510 2709[1529 2624 1533 2554!1533 2554[1534 2536 1525 2535!1525 2535[1515 2531 1506 2543!1506 2543[1502 2548 1499 2553!1499 2553[1500 2548 1502 2544!1502 2544[1519 2469
 1537 2349!1537 2349[1537 2343 1537 2339!1537 2339[#609.53 #913.63 1553 2305.5!1553 2305.5[#612.9 #8FD.F8 1556 2298.5!1556 2298.5[#619.A7 #8EC.E7 1567 2270!1567 2270[1593 2188 1611 2148!1611 2148|1610 2147!1610 2147[#66C.57 #83F.8E 1676
 2045!1676 2045[#66A.EE #7F1.7D 1601 2014.5!1601 2014.5[#63C.1E #7DC.5C 1591 2010!1591 2010[1487 1961 1451 1930!1451 1930[#5A4.C1 #785.01 1431 1895!1431 1895[#528.74 #766.99 1260 1850!1260 1850[#4D6.3D #722.76 1221.5 1810!1221.5 1810
[#4C0.2A #70D.3F 1211.5 1801!1211.5 1801[#4AF.9B #70A.63 1190.5 1803.5!1190.5 1803.5[#491.8B 1806 1163 1806!1163 1806[#44B.54 1806 1045.5 1796!1045.5 1796[#3EC.F5 #6FC.E 970 1776!970 1776[#385.3A #6D6.C5 854 1704!854 1704[#33C.4B #68E.4B
 812.5 1653!812.5 1653[788 #64D.76 788 1575!788 1575[788 1574 768 1549!768 1549[#2EF.81 #5F8.93 748 1513!748 1513[#2B1.E2 #5D8.83 554 1454!554 1454[328 1386 229 1292!229 1292[212 1277 200 1261!200 1261|189 1265"/>
                    <Edge fillStyle0="2" fillStyle1="3" edges="
!1501 2329[1500 2330 1501 2331!1501 2331|1501 2332!1501 2332[1490 2353 1485 2371!1485 2371[1445 2462 1442 2483!1442 2483[1441 2487 1454 2496!1454 2496[1457 2496 1459 2498!1459 2498[1466 2506 1469 2511!1469 2511[1467 2519 1457 2546!1457
 2546[1445 2575 1446 2578!1446 2578[#5A3.D7 #A1B.5B 1451 2625!1451 2625[1448 #A4C.B5 1448 2659!1448 2659|1441 2743!1441 2743[1441 2752 1453 2752!1453 2752[#5B0.E3 2752 1461 2741!1461 2741[#5B1.6E #AC4.C4 1451.5 2779.5!1451.5 2779.5[#5A5.23
 #AD0.97 1435 2799!1435 2799[1427 2824 1415 2876!1415 2876[1397 2940 1387 3006!1387 3006[1382 3032 1360 3069!1360 3069[1328 3120 1323 3131!1323 3131[1316 3144 1302 3198!1302 3198[1288 3250 1288 3261!1288 3261[1288 3270 1271 3306!1271
 3306[1253 3342 1253 3368!1253 3368[#4E9.0C #D2E.AB 1260 3380!1260 3380[#4E1.8A #D56.22 1236 3457!1236 3457[1213 3520 1192 3566!1192 3566[1144 3672 1106 3678!1106 3678[1101 3678 1080 3669!1080 3669[1076 3688 1071 3697!1071 3697[1069 3701
 1067 3703!1067 3703[1059 3708 1025 3712!1025 3712[1015 3714 999 3713!999 3713[982 3711 976 3709!976 3709[974 3711 973 3724!973 3724[964 3736 935 3740!935 3740[901 3744 885 3727!885 3727[872 3708 868 3704!868 3704[858 3715 846 3717!846
 3717[837 3718 827 3714!827 3714[816 3708 813 3705!813 3705[809 3708 802 3715!802 3715[794 3721 785 3723!785 3723[767 3725 745 3711!745 3711[725 3695 717 3698!717 3698|681 3706!681 3706[682 3706 686 3718!686 3718[690 3725 692 3732!692
 3732[693 3746 675 3761!675 3761[666 3772 659 3778!659 3778[653 3780 650 3780!650 3780[#287.AF #EC4.51 645.5 3780.5!645.5 3780.5[#270.BD #EC4.E5 597 3763!597 3763[565 3742 551 3736!551 3736[546 3735 545 3734!545 3734[537 3744 534 3747
!534 3747[527 3752 519 3753!519 3753[513 3754 507 3752!507 3752[504 3749 495 3743!495 3743[485 3761 447 3780!447 3780[396 3785 353 3757!353 3757[326 3738 311 3714!311 3714[310 3713 296 3697!296 3697[292 3691 286 3683!286 3683[287 3689
 289 3697!289 3697[290 3702 291 3708!291 3708[299 3755 259 3760!259 3760[255 3761 248 3750!248 3750[235 3736 217 3697!217 3697[198 3660 174 3600!174 3600[141 3518 125 3476!125 3476|107 3432!107 3432[104 3423 109 3414!109 3414[113 3398
 136 3395!136 3395[143 3393 151 3400!151 3400[162 3404 167 3405!167 3405[171 3409 171 3399!171 3399[171 3391 150 3312!150 3312[128 3234 126 3199!126 3199[125 3193 135 3181!135 3181[141 3167 141 3164!141 3164[139 3136 123 3075!123 3075
[104 3012 103 2988!103 2988[102 2969 104 2963!104 2963[109 2940 139 2942!139 2942[128 2919 105 2824!105 2824[84 2730 84 2705!84 2705[95 2649 107 2593!107 2593[132 2481 131 2473!131 2473[23 2265 21 2237!21 2237[18 2200 28 2176!28 2176
[37 2152 57 2141!57 2141[100 2117 97 2057!97 2057[95 2033 111 2004!111 2004[124 1978 121 1934!121 1934|112 1808!112 1808[#6E.CC #6FE.95 115 1772.5!115 1772.5[#BD.24 #6FC.DE 266 1793!266 1793[282 1794 294 1803!294 1803[325 1826 363 1847
!363 1847[371 1852 381 1853!381 1853[422 1855 462 1842!462 1842[471 1839 480 1840!480 1840[517 1842 547 1864!547 1864[557 1871 567 1877!567 1877[642 1916 714 1951!714 1951[724 1956 732 1963!732 1963[753 1982 779 1996!779 1996[#30D.93
 #7CD.85 784 1999!784 1999[#351.7A #7BC.EF 921 1995!921 1995[925 1992 930 1992!930 1992[985 1996 1040 2002!1040 2002[1045 2002 1050 2002!1050 2002[1063 2002 1071 1999!1071 1999[1075 1998 1080 1998!1080 1998[#44C.3C #7D1.AE 1119 2005.5
!1119 2005.5[#460.65 #7D5.AE 1122 2006!1122 2006[1144 2011 1165 2017!1165 2017[1181 2022 1194 2019!1194 2019[1206 2018 1218 2020!1218 2020[1251 2027 1278 2047!1278 2047[1303 2064 1328 2076!1328 2076[1343 2084 1364 2097!1364 2097[1369
 2101 1374 2105!1374 2105[1392 2125 1404 2144!1404 2144[1409 2153 1427 2152!1427 2152[1449 2151 1456 2173!1456 2173[1458 2179 1463 2183!1463 2183[1469 2188 1473 2199!1473 2199[1475 2203 1478 2207!1478 2207[#5CF.B6 #8A8.B6 1500.5 2221.5
!1500.5 2221.5|1501 2222!1501 2222[1506 2224 1507 2226!1507 2226[1510 2229 1511 2234!1511 2234[1512 2237 1513 2239!1513 2239[#5F3.42 #8CF.1E 1528 2272!1528 2272[#5F6.58 #8E3.D8 1524.5 2280!1524.5 2280[#5F2.E5 #8EB.58 1521.5 2287!1521.5
 2287[#5EF.A4 #8F2.57 1518 2294!1518 2294[1514 2300 1513 2305"/>
                    <Edge fillStyle0="2" fillStyle1="1" edges="
!1513 2305[1510 2315 1506 2323!1506 2323[1503 2326 1501 2329"/>
                    <Edge fillStyle0="1" fillStyle1="3" edges="
!1513 2305[1506 2318 1501 2329"/>
                    <Edge fillStyle1="2" edges="
!-39 2209[-42 2210 -43 2210!-43 2210|-44 2211!-44 2211|-39 2209"/>
                    <Edge cubics="!1610 2147(;1610,2147 1611,2148 1611,2148q1610 2147 1611 2148);"/>
                    <Edge cubics="!1537 2339(;1537,2342 1537,2345 1537,2349q1537 2339Q1537 2343q1537 2349);"/>
                    <Edge cubics="!1506 2323(;1509,2318 1511,2312 1513,2305q1506 2323Q1510 2315q1513 2305);"/>
                    <Edge cubics="!1518 2294(;1515,2298 1514,2302 1513,2305q1518 2294Q1514 2300q1513 2305);"/>
                    <Edge cubics="!1611 2148(;1599,2175 1584,2215 1567,2270q1611 2148Q1593 2188q1567 2270);"/>
                    <Edge cubics="!1501 2332(;1494,2346 1488,2359 1485,2371q1501 2332Q1490 2353q1485 2371);"/>
                    <Edge cubics="!1501 2332(;1501,2332 1501,2331 1501,2331q1501 2332 1501 2331);"/>
                    <Edge cubics="!1501 2329(;1500,2330 1500,2330 1501,2331q1501 2329Q1500 2330q1501 2331);"/>
                    <Edge cubics="!1454 2496(;1455,2496 1458,2497 1459,2498q1454 2496Q1457 2496q1459 2498);"/>
                    <Edge cubics="!1502 2544(;1501,2547 1500,2550 1499,2553q1502 2544Q1500 2548q1499 2553);"/>
                    <Edge cubics="!1469 2511(;1467,2516 1464,2528 1457,2546q1469 2511Q1467 2519q1457 2546);"/>
                    <Edge cubics="!1459 2498(;1464,2503 1467,2508 1469,2511q1459 2498Q1466 2506q1469 2511);"/>
                    <Edge cubics="!1442 2483(;1441,2486 1446,2490 1454,2496q1442 2483Q1441 2487q1454 2496);"/>
                    <Edge cubics="!1446 2578(;1445,2587 1448,2614 1458,2659q1446 2578Q1443 2591q1458 2659);"/>
                    <Edge cubics="!1477 2627(;1471,2640 1464,2651 1458,2659q1477 2627Q1467 2647q1458 2659);"/>
                    <Edge cubics="!1474 2658(;1475,2647 1476,2637 1477,2627q1474 2658Q1475 2642q1477 2627);"/>
                    <Edge cubics="!1457 2546(;1449,2565 1445,2576 1446,2578q1457 2546Q1445 2575q1446 2578);"/>
                    <Edge cubics="!1467 2708(;1467,2717 1459,2754 1442,2817q1467 2708Q1467 2722q1442 2817);"/>
                    <Edge cubics="!1481 2799(;1482,2808 1483,2827 1482,2856q1481 2799Q1483 2812q1482 2856);"/>
                    <Edge cubics="!1448 2832(;1448,2832 1448,2831 1448,2831q1448 2832 1448 2831);"/>
                    <Edge cubics="!1442 2817(;1439,2824 1437,2831 1436,2838q1442 2817Q1438 2827q1436 2838);"/>
                    <Edge cubics="!1443 2820(;1442,2819 1442,2818 1442,2817q1443 2820Q1442 2818q1442 2817);"/>
                    <Edge cubics="!1448 2831(;1447,2830 1445,2826 1443,2820q1448 2831Q1446 2829q1443 2820);"/>
                    <Edge cubics="!1464 2693(;1465,2697 1466,2702 1467,2708q1464 2693Q1465 2699q1467 2708);"/>
                    <Edge cubics="!1464 2693(;1469,2677 1472,2665 1474,2658q1464 2693Q1471 2669q1474 2658);"/>
                    <Edge cubics="!1458 2659(;1459,2668 1461,2680 1464,2693q1458 2659Q1460 2673q1464 2693);"/>
                    <Edge cubics="!1533 2554(;1530,2601 1522,2652 1510,2709q1533 2554Q1529 2624q1510 2709);"/>
                    <Edge cubics="!1506 2543(;1512,2535 1519,2532 1525,2535q1506 2543Q1515 2531q1525 2535);"/>
                    <Edge cubics="!1525 2535(;1531,2536 1534,2542 1533,2554q1525 2535Q1534 2536q1533 2554);"/>
                    <Edge cubics="!1537 2349(;1525,2429 1513,2494 1502,2544q1537 2349Q1519 2469q1502 2544);"/>
                    <Edge cubics="!1510 2709(;1500,2748 1490,2778 1481,2799q1510 2709Q1496 2768q1481 2799);"/>
                    <Edge cubics="!1485 2371(;1458,2432 1443,2469 1442,2483q1485 2371Q1445 2462q1442 2483);"/>
                    <Edge cubics="!1499 2553(;1501,2550 1503,2546 1506,2543q1499 2553Q1502 2548q1506 2543);"/>
                    <Edge cubics="!1513 2305(;1508,2314 1505,2322 1501,2329q1513 2305Q1506 2318q1501 2329);"/>
                    <Edge cubics="!1501 2329(;1502,2327 1505,2325 1506,2323q1501 2329Q1503 2326q1506 2323);"/>
                    <Edge cubics="!-54 1312(;-54,1295 -53,1281 -51,1268q-54 1312Q-54 1287q-51 1268);"/>
                    <Edge cubics="!-60 1651(;-92,1575 -110,1525 -111,1502q-60 1651Q-108 1537q-111 1502);"/>
                    <Edge cubics="!-111 1502(;-114,1455 -106,1446 -86,1476q-111 1502Q-116 1431q-86 1476);"/>
                    <Edge cubics="!-81 1481(;-81,1481 -80,1483 -80,1483q-81 1481 -80 1483);"/>
                    <Edge cubics="!-80 1483(;-80,1483 -80,1481 -80,1481q-80 1483 -80 1481);"/>
                    <Edge cubics="!-86 1476(;-84,1478 -83,1480 -81,1481q-86 1476Q-84 1479q-81 1481);"/>
                    <Edge cubics="!-53 1774(;-69,1744 -78,1724 -77,1714q-53 1774Q-78 1729q-77 1714);"/>
                    <Edge cubics="!-58 1840(;-62,1813 -59,1791 -53,1774q-58 1840Q-63 1800q-53 1774);"/>
                    <Edge cubics="!121 1934(;121,1934 112,1808 112,1808q121 1934 112 1808);"/>
                    <Edge cubics="!-77 1714(;-80,1690 -75,1669 -60,1651q-77 1714Q-82 1678q-60 1651);"/>
                    <Edge cubics="!-80 1481(;-83,1400 -75,1344 -54,1312q-80 1481Q-84 1360q-54 1312);"/>
                    <Edge cubics="!57 2141(;86,2125 99,2097 97,2057q57 2141Q100 2117q97 2057);"/>
                    <Edge cubics="!97 2057(;96,2041 100,2023 111,2004q97 2057Q95 2033q111 2004);"/>
                    <Edge cubics="!-70 2056(;-67,1999 -62,1963 -52,1950q-70 2056Q-66 1970q-52 1950);"/>
                    <Edge cubics="!-71 2109(;-72,2092 -72,2075 -70,2056q-71 2109Q-74 2084q-70 2056);"/>
                    <Edge cubics="!-84 2100(;-81,2099 -78,2098 -76,2098q-84 2100Q-79 2098q-76 2098);"/>
                    <Edge cubics="!-87 2112(;-88,2106 -87,2102 -84,2100q-87 2112Q-88 2103q-84 2100);"/>
                    <Edge cubics="!-76 2098(;-75,2101 -72,2105 -71,2109q-76 2098Q-74 2103q-71 2109);"/>
                    <Edge cubics="!-43 2210(;-43,2210 -44,2211 -44,2211q-43 2210 -44 2211);"/>
                    <Edge cubics="!-39 2209(;-41,2210 -42,2210 -43,2210q-39 2209Q-42 2210q-43 2210);"/>
                    <Edge cubics="!-39 2209(;-39,2209 -44,2211 -44,2211q-39 2209 -44 2211);"/>
                    <Edge cubics="!-7 2514(;-7,2514 -6,2513 -6,2513q-7 2514 -6 2513);"/>
                    <Edge cubics="!-10 2512(;-9,2517 -8,2525 -7,2534q-10 2512Q-9 2520q-7 2534);"/>
                    <Edge cubics="!-31 2528(;-23,2489 -16,2484 -10,2512q-31 2528Q-19 2470q-10 2512);"/>
                    <Edge cubics="!-7 2534(;-7,2523 -7,2516 -7,2514q-7 2534Q-7 2517q-7 2514);"/>
                    <Edge cubics="!107 2593(;123,2518 132,2478 131,2473q107 2593Q132 2481q131 2473);"/>
                    <Edge cubics="!105 2824(;91,2761 84,2722 84,2705q105 2824Q84 2730q84 2705);"/>
                    <Edge cubics="!-15 2864(;-16,2851 -12,2843 -5,2838q-15 2864Q-17 2845q-5 2838);"/>
                    <Edge cubics="!-5 2838(;-7,2830 -9,2822 -11,2813q-5 2838Q-8 2826q-11 2813);"/>
                    <Edge cubics="!84 2705(;91,2668 99,2630 107,2593q84 2705Q95 2649q107 2593);"/>
                    <Edge cubics="!-44 2658(;-47,2627 -43,2584 -31,2528q-44 2658Q-48 2612q-31 2528);"/>
                    <Edge cubics="!-11 2813(;-32,2735 -43,2683 -44,2658q-11 2813Q-42 2696q-44 2658);"/>
                    <Edge cubics="!-6 2513(;-7,2498 -34,2365 -87,2112q-6 2513Q-8 2491q-87 2112);"/>
                    <Edge cubics="!131 2473(;59,2334 23,2256 21,2237q131 2473Q23 2265q21 2237);"/>
                    <Edge cubics="!-52 1950(;-53,1927 -55,1891 -58,1840q-52 1950Q-53 1916q-58 1840);"/>
                    <Edge cubics="!111 2004(;120,1987 123,1963 121,1934q111 2004Q124 1978q121 1934);"/>
                    <Edge cubics="!103 2988(;102,2975 103,2967 104,2963q103 2988Q102 2969q104 2963);"/>
                    <Edge cubics="!104 2963(;108,2948 119,2941 139,2942q104 2963Q109 2940q139 2942);"/>
                    <Edge cubics="!-20 3025(;-21,3020 -17,3008 -6,2989q-20 3025Q-22 3017q-6 2989);"/>
                    <Edge cubics="!-15 3037(;-18,3034 -19,3030 -20,3025q-15 3037Q-19 3033q-20 3025);"/>
                    <Edge cubics="!12 3046(;12,3046 11,3046 11,3046q12 3046 11 3046);"/>
                    <Edge cubics="!11 3046(;-3,3048 -11,3045 -15,3037q11 3046Q-9 3049q-15 3037);"/>
                    <Edge cubics="!-6 2989(;-3,2982 0,2977 3,2973q-6 2989Q-1 2979q3 2973);"/>
                    <Edge cubics="!141 3164(;140,3145 134,3116 123,3075q141 3164Q139 3136q123 3075);"/>
                    <Edge cubics="!135 3181(;139,3172 141,3166 141,3164q135 3181Q141 3167q141 3164);"/>
                    <Edge cubics="!123 3075(;111,3033 104,3004 103,2988q123 3075Q104 3012q103 2988);"/>
                    <Edge cubics="!41 3384(;41,3384 42,3383 42,3383q41 3384 42 3383);"/>
                    <Edge cubics="!35 3410(;33,3395 36,3387 41,3384q35 3410Q32 3388q41 3384);"/>
                    <Edge cubics="!171 3399(;171,3394 164,3365 150,3312q171 3399Q171 3391q150 3312);"/>
                    <Edge cubics="!109 3414(;112,3403 121,3397 136,3395q109 3414Q113 3398q136 3395);"/>
                    <Edge cubics="!107 3432(;105,3426 105,3420 109,3414q107 3432Q104 3423q109 3414);"/>
                    <Edge cubics="!136 3395(;140,3394 146,3395 151,3400q136 3395Q143 3393q151 3400);"/>
                    <Edge cubics="!151 3400(;159,3403 163,3404 167,3405q151 3400Q162 3404q167 3405);"/>
                    <Edge cubics="!167 3405(;170,3408 171,3406 171,3399q167 3405Q171 3409q171 3399);"/>
                    <Edge cubics="!42 3383(;35,3350 27,3300 21,3231q42 3383Q30 3334q21 3231);"/>
                    <Edge cubics="!150 3312(;136,3260 127,3222 126,3199q150 3312Q128 3234q126 3199);"/>
                    <Edge cubics="!21 3231(;16,3139 13,3077 12,3046q21 3231Q14 3093q12 3046);"/>
                    <Edge cubics="!126 3199(;125,3195 128,3189 135,3181q126 3199Q125 3193q135 3181);"/>
                    <Edge cubics="!33 3522(;32,3520 31,3517 31,3514q33 3522Q31 3519q31 3514);"/>
                    <Edge cubics="!31 3514(;30,3501 37,3496 50,3498q31 3514Q30 3495q50 3498);"/>
                    <Edge cubics="!120 3620(;99,3622 83,3607 69,3574q120 3620Q89 3623q69 3574);"/>
                    <Edge cubics="!138 3658(;134,3645 127,3633 120,3620q138 3658Q132 3639q120 3620);"/>
                    <Edge cubics="!174 3600(;152,3545 136,3504 125,3476q174 3600Q141 3518q125 3476);"/>
                    <Edge cubics="!69 3574(;49,3558 37,3541 33,3522q69 3574Q38 3550q33 3522);"/>
                    <Edge cubics="!172 3751(;172,3746 172,3743 172,3741q172 3751Q172 3744q172 3741);"/>
                    <Edge cubics="!50 3498(;39,3439 33,3409 35,3410q50 3498Q33 3409q35 3410);"/>
                    <Edge cubics="!125 3476(;125,3476 107,3432 107,3432q125 3476 107 3432);"/>
                    <Edge cubics="!1404 3007(;1404,3006 1405,3005 1407,3005q1404 3007Q1404 3005q1407 3005);"/>
                    <Edge cubics="!1454 2959(;1449,2978 1443,2994 1439,3008q1454 2959Q1446 2987q1439 3008);"/>
                    <Edge cubics="!1439 3008(;1440,3013 1440,3019 1440,3027q1439 3008Q1440 3015q1440 3027);"/>
                    <Edge cubics="!1369 3103(;1367,3102 1365,3100 1364,3098q1369 3103Q1366 3101q1364 3098);"/>
                    <Edge cubics="!1364 3098(;1363,3096 1362,3093 1363,3090q1364 3098Q1362 3095q1363 3090);"/>
                    <Edge cubics="!1423 3068(;1415,3083 1405,3093 1395,3100q1423 3068Q1411 3090q1395 3100);"/>
                    <Edge cubics="!1382 3029(;1377,3045 1370,3063 1363,3084q1382 3029Q1374 3053q1363 3084);"/>
                    <Edge cubics="!1440 3027(;1439,3036 1433,3049 1423,3068q1440 3027Q1438 3040q1423 3068);"/>
                    <Edge cubics="!1382 3029(;1388,3020 1394,3013 1404,3007q1382 3029Q1390 3016q1404 3007);"/>
                    <Edge cubics="!1398 2978(;1394,2991 1390,3008 1382,3029q1398 2978Q1393 2997q1382 3029);"/>
                    <Edge cubics="!1395 3100(;1391,3113 1382,3136 1368,3170q1395 3100Q1389 3119q1368 3170);"/>
                    <Edge cubics="!1367 3216(;1367,3216 1330,3344 1330,3344q1367 3216 1330 3344);"/>
                    <Edge cubics="!1303 3282(;1308,3265 1312,3253 1314,3246q1303 3282Q1311 3257q1314 3246);"/>
                    <Edge cubics="!1292 3315(;1296,3300 1299,3289 1303,3282q1292 3315Q1298 3293q1303 3282);"/>
                    <Edge cubics="!1314 3246(;1315,3241 1317,3235 1320,3230q1314 3246Q1315 3238q1320 3230);"/>
                    <Edge cubics="!1356 3198(;1364,3196 1368,3202 1367,3216q1356 3198Q1368 3195q1367 3216);"/>
                    <Edge cubics="!1320 3230(;1336,3173 1353,3131 1369,3103q1320 3230Q1344 3145q1369 3103);"/>
                    <Edge cubics="!1344 3133(;1317,3198 1304,3232 1305,3235q1344 3133Q1304 3230q1305 3235);"/>
                    <Edge cubics="!1305 3235(;1304,3236 1292,3277 1267,3358q1305 3235Q1304 3236q1267 3358);"/>
                    <Edge cubics="!1267 3358(;1281,3336 1288,3322 1292,3315q1267 3358Q1287 3325q1292 3315);"/>
                    <Edge cubics="!1368 3170(;1364,3181 1359,3190 1356,3198q1368 3170Q1362 3186q1356 3198);"/>
                    <Edge cubics="!1245 3541(;1247,3543 1248,3551 1248,3565q1245 3541Q1248 3544q1248 3565);"/>
                    <Edge cubics="!1236 3457(;1221,3499 1207,3535 1192,3566q1236 3457Q1213 3520q1192 3566);"/>
                    <Edge cubics="!1283 3436(;1269,3479 1256,3514 1245,3541q1283 3436Q1261 3500q1245 3541);"/>
                    <Edge cubics="!1106 3678(;1103,3678 1094,3675 1080,3669q1106 3678Q1101 3678q1080 3669);"/>
                    <Edge cubics="!1192 3566(;1161,3637 1131,3674 1106,3678q1192 3566Q1144 3672q1106 3678);"/>
                    <Edge cubics="!1077 3815(;1077,3815 1076,3817 1076,3817q1077 3815 1076 3817);"/>
                    <Edge cubics="!1077 3815(;1077,3815 1088,3811 1088,3811q1077 3815 1088 3811);"/>
                    <Edge cubics="!1109 3817(;1097,3819 1090,3817 1088,3811q1109 3817Q1091 3820q1088 3811);"/>
                    <Edge cubics="!1330 3344(;1314,3384 1298,3415 1283,3436q1330 3344Q1306 3404q1283 3436);"/>
                    <Edge cubics="!1267 3358(;1258,3386 1248,3419 1236,3457q1267 3358Q1254 3400q1236 3457);"/>
                    <Edge cubics="!353 3757(;335,3744 320,3730 311,3714q353 3757Q326 3738q311 3714);"/>
                    <Edge cubics="!259 3760(;256,3761 253,3757 248,3750q259 3760Q255 3761q248 3750);"/>
                    <Edge cubics="!258 3888(;240,3879 222,3858 204,3826q258 3888Q231 3874q204 3826);"/>
                    <Edge cubics="!260 3903(;258,3899 257,3895 258,3892q260 3903Q257 3897q258 3892);"/>
                    <Edge cubics="!281 3908(;271,3909 265,3907 260,3903q281 3908Q267 3909q260 3903);"/>
                    <Edge cubics="!258 3892(;258,3891 258,3889 258,3888q258 3892Q258 3890q258 3888);"/>
                    <Edge cubics="!337 3832(;337,3834 337,3837 337,3840q337 3832Q337 3835q337 3840);"/>
                    <Edge cubics="!341 3836(;340,3835 339,3833 337,3832q341 3836Q340 3834q337 3832);"/>
                    <Edge cubics="!361 3861(;353,3852 347,3844 341,3836q361 3861Q350 3848q341 3836);"/>
                    <Edge cubics="!337 3840(;335,3845 334,3851 332,3857q337 3840Q334 3848q332 3857);"/>
                    <Edge cubics="!332 3857(;320,3888 304,3905 281,3908q332 3857Q315 3903q281 3908);"/>
                    <Edge cubics="!291 3708(;296,3739 286,3757 259,3760q291 3708Q299 3755q259 3760);"/>
                    <Edge cubics="!534 3747(;529,3750 525,3752 519,3753q534 3747Q527 3752q519 3753);"/>
                    <Edge cubics="!551 3736(;547,3735 546,3735 545,3734q551 3736Q546 3735q545 3734);"/>
                    <Edge cubics="!597 3763(;576,3749 561,3740 551,3736q597 3763Q565 3742q551 3736);"/>
                    <Edge cubics="!545 3734(;540,3741 535,3745 534,3747q545 3734Q537 3744q534 3747);"/>
                    <Edge cubics="!495 3743(;489,3755 472,3767 447,3780q495 3743Q485 3761q447 3780);"/>
                    <Edge cubics="!507 3752(;505,3750 501,3747 495,3743q507 3752Q504 3749q495 3743);"/>
                    <Edge cubics="!481 3903(;473,3912 465,3918 454,3920q481 3903Q470 3917q454 3920);"/>
                    <Edge cubics="!493 3880(;490,3883 485,3891 481,3903q493 3880Q487 3885q481 3903);"/>
                    <Edge cubics="!496 3881(;496,3881 493,3880 493,3880q496 3881 493 3880);"/>
                    <Edge cubics="!505 3898(;499,3893 497,3887 496,3881q505 3898Q497 3890q496 3881);"/>
                    <Edge cubics="!568 3846(;567,3846 567,3849 567,3855q568 3846Q567 3846q567 3855);"/>
                    <Edge cubics="!598 3849(;588,3850 580,3849 575,3845q598 3849Q583 3851q575 3845);"/>
                    <Edge cubics="!575 3845(;570,3845 568,3845 568,3846q575 3845Q568 3845q568 3846);"/>
                    <Edge cubics="!567 3855(;568,3869 568,3878 567,3882q567 3855Q568 3876q567 3882);"/>
                    <Edge cubics="!567 3882(;562,3898 550,3907 531,3910q567 3882Q558 3906q531 3910);"/>
                    <Edge cubics="!531 3910(;520,3911 511,3907 505,3898q531 3910Q515 3911q505 3898);"/>
                    <Edge cubics="!519 3753(;515,3754 510,3753 507,3752q519 3753Q513 3754q507 3752);"/>
                    <Edge cubics="!454 3920(;428,3923 397,3904 361,3861q454 3920Q415 3925q361 3861);"/>
                    <Edge cubics="!447 3780(;413,3783 382,3776 353,3757q447 3780Q396 3785q353 3757);"/>
                    <Edge cubics="!785 3723(;773,3724 759,3720 745,3711q785 3723Q767 3725q745 3711);"/>
                    <Edge cubics="!802 3715(;796,3719 791,3722 785,3723q802 3715Q794 3721q785 3723);"/>
                    <Edge cubics="!813 3705(;810,3707 807,3710 802,3715q813 3705Q809 3708q802 3715);"/>
                    <Edge cubics="!827 3714(;819,3710 815,3707 813,3705q827 3714Q816 3708q813 3705);"/>
                    <Edge cubics="!659 3778(;655,3779 652,3780 650,3780q659 3778Q653 3780q650 3780);"/>
                    <Edge cubics="!675 3761(;670,3768 664,3774 659,3778q675 3761Q666 3772q659 3778);"/>
                    <Edge cubics="!692 3732(;693,3741 687,3751 675,3761q692 3732Q693 3746q675 3761);"/>
                    <Edge cubics="!681 3706(;682,3706 683,3710 686,3718q681 3706Q682 3706q686 3718);"/>
                    <Edge cubics="!686 3718(;689,3723 690,3727 692,3732q686 3718Q690 3725q692 3732);"/>
                    <Edge cubics="!717 3698(;717,3698 681,3706 681,3706q717 3698 681 3706);"/>
                    <Edge cubics="!687 3837(;682,3845 675,3849 665,3850q687 3837Q680 3849q665 3850);"/>
                    <Edge cubics="!637 3848(;633,3841 628,3834 625,3829q637 3848Q630 3837q625 3829);"/>
                    <Edge cubics="!709 3838(;699,3837 693,3834 689,3831q709 3838Q695 3836q689 3831);"/>
                    <Edge cubics="!689 3831(;688,3833 688,3835 687,3837q689 3831Q688 3834q687 3837);"/>
                    <Edge cubics="!797 3826(;794,3826 785,3828 772,3833q797 3826Q792 3826q772 3833);"/>
                    <Edge cubics="!841 3860(;815,3837 801,3825 797,3826q841 3860Q802 3825q797 3826);"/>
                    <Edge cubics="!772 3833(;762,3836 755,3839 752,3840q772 3833Q757 3838q752 3840);"/>
                    <Edge cubics="!752 3840(;734,3842 720,3841 709,3838q752 3840Q725 3843q709 3838);"/>
                    <Edge cubics="!745 3711(;732,3700 722,3696 717,3698q745 3711Q725 3695q717 3698);"/>
                    <Edge cubics="!999 3713(;987,3712 980,3710 976,3709q999 3713Q982 3711q976 3709);"/>
                    <Edge cubics="!1025 3712(;1018,3713 1009,3714 999,3713q1025 3712Q1015 3714q999 3713);"/>
                    <Edge cubics="!976 3709(;975,3710 974,3715 973,3724q976 3709Q974 3711q973 3724);"/>
                    <Edge cubics="!868 3704(;862,3711 854,3716 846,3717q868 3704Q858 3715q846 3717);"/>
                    <Edge cubics="!885 3727(;876,3714 870,3707 868,3704q885 3727Q872 3708q868 3704);"/>
                    <Edge cubics="!935 3740(;912,3743 896,3738 885,3727q935 3740Q901 3744q885 3727);"/>
                    <Edge cubics="!936 3872(;927,3881 919,3886 910,3888q936 3872Q923 3885q910 3888);"/>
                    <Edge cubics="!910 3888(;906,3889 904,3889 903,3890q910 3888Q905 3889q903 3890);"/>
                    <Edge cubics="!1051 3848(;1041,3850 1033,3848 1029,3841q1051 3848Q1035 3851q1029 3841);"/>
                    <Edge cubics="!1029 3841(;1029,3841 1024,3831 1024,3831q1029 3841 1024 3831);"/>
                    <Edge cubics="!1024 3831(;1019,3834 1008,3843 994,3859q1024 3831Q1016 3835q994 3859);"/>
                    <Edge cubics="!994 3859(;984,3866 974,3872 963,3875q994 3859Q980 3870q963 3875);"/>
                    <Edge cubics="!963 3875(;960,3875 957,3876 955,3877q963 3875Q958 3875q955 3877);"/>
                    <Edge cubics="!955 3877(;947,3878 940,3876 936,3872q955 3877Q943 3878q936 3872);"/>
                    <Edge cubics="!973 3724(;968,3732 955,3737 935,3740q973 3724Q964 3736q935 3740);"/>
                    <Edge cubics="!903 3890(;889,3891 868,3881 841,3860q903 3890Q881 3892q841 3860);"/>
                    <Edge cubics="!846 3717(;840,3718 833,3717 827,3714q846 3717Q837 3718q827 3714);"/>
                    <Edge cubics="!625 3829(;615,3842 605,3848 598,3849q625 3829Q610 3848q598 3849);"/>
                    <Edge cubics="!1067 3703(;1061,3706 1048,3709 1025,3712q1067 3703Q1059 3708q1025 3712);"/>
                    <Edge cubics="!1076 3817(;1075,3835 1067,3845 1051,3848q1076 3817Q1075 3844q1051 3848);"/>
                    <Edge cubics="!1407 3005(;1407,2954 1421,2897 1448,2832q1407 3005Q1407 2929q1448 2832);"/>
                    <Edge cubics="!1436 2838(;1411,2925 1398,2972 1398,2978q1436 2838Q1398 2969q1398 2978);"/>
                    <Edge cubics="!1482 2856(;1481,2871 1471,2905 1454,2959q1482 2856Q1479 2878q1454 2959);"/>
                    <Edge cubics="!204 3826(;204,3826 172,3751 172,3751q204 3826 172 3751);"/>
                    <Edge cubics="!139 2942(;132,2927 121,2887 105,2824q139 2942Q128 2919q105 2824);"/>
                    <Edge cubics="!3 2973(;-8,2907 -13,2871 -15,2864q3 2973Q-13 2874q-15 2864);"/>
                    <Edge cubics="!28 2176(;33,2160 43,2148 57,2141q28 2176Q37 2152q57 2141);"/>
                    <Edge cubics="!21 2237(;19,2212 21,2192 28,2176q21 2237Q18 2200q28 2176);"/>
                    <Edge cubics="!-81 1179(;-62,1196 -40,1212 -17,1225q-81 1179Q-52 1205q-17 1225);"/>
                    <Edge cubics="!189 1265(;182,1268 173,1269 161,1269q189 1265Q179 1269q161 1269);"/>
                    <Edge cubics="!200 1261(;200,1261 189,1265 189,1265q200 1261 189 1265);"/>
                    <Edge cubics="!229 1292(;218,1282 208,1272 200,1261q229 1292Q212 1277q200 1261);"/>
                    <Edge cubics="!161 1269(;96,1269 37,1254 -17,1225q161 1269Q63 1269q-17 1225);"/>
                    <Edge cubics="!-51 1268(;-67,1251 -78,1221 -81,1179q-51 1268Q-76 1242q-81 1179);"/>
                    <Edge cubics="!554 1454(;403,1409 295,1355 229,1292q554 1454Q328 1386q229 1292);"/>
                    <Edge cubics="!153 3697(;148,3685 144,3672 138,3658q153 3697Q146 3679q138 3658);"/>
                    <Edge cubics="!217 3697(;205,3672 191,3640 174,3600q217 3697Q198 3660q174 3600);"/>
                    <Edge cubics="!248 3750(;240,3741 229,3723 217,3697q248 3750Q235 3736q217 3697);"/>
                    <Edge cubics="!172 3741(;167,3728 160,3714 153,3697q172 3741Q163 3722q153 3697);"/>
                    <Edge cubics="!296 3697(;293,3693 290,3688 286,3683q296 3697Q292 3691q286 3683);"/>
                    <Edge cubics="!289 3697(;290,3700 290,3704 291,3708q289 3697Q290 3702q291 3708);"/>
                    <Edge cubics="!286 3683(;287,3687 288,3692 289,3697q286 3683Q287 3689q289 3697);"/>
                    <Edge cubics="!311 3714(;310,3713 305,3708 296,3697q311 3714Q310 3713q296 3697);"/>
                    <Edge cubics="!1071 3697(;1070,3700 1068,3702 1067,3703q1071 3697Q1069 3701q1067 3703);"/>
                    <Edge cubics="!1080 3669(;1077,3682 1075,3691 1071,3697q1080 3669Q1076 3688q1071 3697);"/>
                    <Edge cubics="!1248 3565(;1227,3617 1208,3661 1191,3697q1248 3565Q1216 3643q1191 3697);"/>
                    <Edge cubics="!1191 3697(;1155,3775 1128,3815 1109,3817q1191 3697Q1137 3814q1109 3817);"/>
                    <Edge cubics="!1363 3084(;1363,3084 1363,3088 1363,3088q1363 3084 1363 3088);"/>
                    <Edge cubics="!1363 3089(;1363,3090 1363,3090 1363,3090q1363 3089Q1363 3090q1363 3090);"/>
                    <Edge cubics="!1363 3088(;1363,3088 1363,3089 1363,3089q1363 3088 1363 3089);"/>
                    <Edge cubics="!1363 3089(;1357,3104 1351,3118 1344,3133q1363 3089Q1354 3111q1344 3133);"/>
                    <Edge cubics="!112 1808(;111,1797 112,1785 115,1773q112 1808Q111 1791q115 1773);"/>
                    <Edge cubics="!115 1773(;164,1784 215,1790 266,1793q115 1773Q189 1789q266 1793);"/>
                    <Edge cubics="!266 1793(;277,1794 286,1797 294,1803q266 1793Q282 1794q294 1803);"/>
                    <Edge cubics="!294 1803(;315,1818 338,1833 363,1847q294 1803Q325 1826q363 1847);"/>
                    <Edge cubics="!363 1847(;368,1850 374,1852 381,1853q363 1847Q371 1852q381 1853);"/>
                    <Edge cubics="!788 1575(;788,1574 781,1566 768,1549q788 1575Q788 1574q768 1549);"/>
                    <Edge cubics="!768 1549(;757,1536 751,1524 748,1513q768 1549Q752 1529q748 1513);"/>
                    <Edge cubics="!462 1842(;468,1840 474,1839 480,1840q462 1842Q471 1839q480 1840);"/>
                    <Edge cubics="!480 1840(;505,1841 527,1849 547,1864q480 1840Q517 1842q547 1864);"/>
                    <Edge cubics="!547 1864(;554,1869 560,1873 567,1877q547 1864Q557 1871q567 1877);"/>
                    <Edge cubics="!714 1951(;721,1954 727,1958 732,1963q714 1951Q724 1956q732 1963);"/>
                    <Edge cubics="!567 1877(;617,1903 666,1928 714,1951q567 1877Q642 1916q714 1951);"/>
                    <Edge cubics="!381 1853(;408,1854 435,1851 462,1842q381 1853Q422 1855q462 1842);"/>
                    <Edge cubics="!748 1513(;709,1502 645,1483 554,1454q748 1513Q690 1497q554 1454);"/>
                    <Edge cubics="!854 1704(;837,1687 823,1670 813,1653q854 1704Q828 1678q813 1653);"/>
                    <Edge cubics="!1212 1801(;1204,1802 1197,1803 1191,1804q1212 1801Q1200 1802q1191 1804);"/>
                    <Edge cubics="!1191 1804(;1177,1805 1168,1806 1163,1806q1191 1804Q1170 1806q1163 1806);"/>
                    <Edge cubics="!1163 1806(;1120,1806 1081,1803 1046,1796q1163 1806Q1099 1806q1046 1796);"/>
                    <Edge cubics="!970 1776(;924,1759 885,1735 854,1704q970 1776Q901 1751q854 1704);"/>
                    <Edge cubics="!1046 1796(;1019,1791 993,1785 970,1776q1046 1796Q1005 1789q970 1776);"/>
                    <Edge cubics="!1260 1850(;1245,1834 1233,1821 1222,1810q1260 1850Q1238 1826q1222 1810);"/>
                    <Edge cubics="!1451 1930(;1447,1927 1440,1915 1431,1895q1451 1930Q1445 1925q1431 1895);"/>
                    <Edge cubics="!1431 1895(;1357,1895 1300,1880 1260,1850q1431 1895Q1320 1895q1260 1850);"/>
                    <Edge cubics="!1222 1810(;1218,1807 1215,1804 1212,1801q1222 1810Q1216 1805q1212 1801);"/>
                    <Edge cubics="!813 1653(;796,1626 788,1600 788,1575q813 1653Q788 1613q788 1575);"/>
                    <Edge cubics="!1601 2015(;1598,2013 1594,2011 1591,2010q1601 2015Q1596 2012q1591 2010);"/>
                    <Edge cubics="!1427 2152(;1442,2151 1451,2158 1456,2173q1427 2152Q1449 2151q1456 2173);"/>
                    <Edge cubics="!1456 2173(;1457,2177 1460,2180 1463,2183q1456 2173Q1458 2179q1463 2183);"/>
                    <Edge cubics="!1463 2183(;1467,2186 1470,2192 1473,2199q1463 2183Q1469 2188q1473 2199);"/>
                    <Edge cubics="!1473 2199(;1474,2202 1476,2204 1478,2207q1473 2199Q1475 2203q1478 2207);"/>
                    <Edge cubics="!1478 2207(;1485,2214 1492,2219 1501,2222q1478 2207Q1488 2217q1501 2222);"/>
                    <Edge cubics="!1501 2222(;1501,2222 1501,2222 1501,2222q1501 2222);"/>
                    <Edge cubics="!1501 2222(;1504,2223 1506,2225 1507,2226q1501 2222Q1506 2224q1507 2226);"/>
                    <Edge cubics="!1218 2020(;1240,2025 1260,2034 1278,2047q1218 2020Q1251 2027q1278 2047);"/>
                    <Edge cubics="!1278 2047(;1295,2058 1311,2068 1328,2076q1278 2047Q1303 2064q1328 2076);"/>
                    <Edge cubics="!1328 2076(;1338,2081 1350,2088 1364,2097q1328 2076Q1343 2084q1364 2097);"/>
                    <Edge cubics="!1364 2097(;1367,2100 1371,2102 1374,2105q1364 2097Q1369 2101q1374 2105);"/>
                    <Edge cubics="!1374 2105(;1386,2118 1396,2131 1404,2144q1374 2105Q1392 2125q1404 2144);"/>
                    <Edge cubics="!1528 2272(;1527,2275 1526,2277 1525,2280q1528 2272Q1526 2276q1525 2280);"/>
                    <Edge cubics="!1525 2280(;1524,2282 1523,2284 1522,2287q1525 2280Q1523 2283q1522 2287);"/>
                    <Edge cubics="!1556 2299(;1555,2301 1554,2303 1553,2306q1556 2299Q1555 2302q1553 2306);"/>
                    <Edge cubics="!1553 2306(;1548,2317 1542,2328 1537,2339q1553 2306Q1545 2323q1537 2339);"/>
                    <Edge cubics="!1567 2270(;1564,2280 1560,2290 1556,2299q1567 2270Q1562 2285q1556 2299);"/>
                    <Edge cubics="!1511 2234(;1512,2236 1512,2238 1513,2239q1511 2234Q1512 2237q1513 2239);"/>
                    <Edge cubics="!1513 2239(;1520,2250 1525,2261 1528,2272q1513 2239Q1523 2255q1528 2272);"/>
                    <Edge cubics="!1522 2287(;1521,2289 1519,2291 1518,2294q1522 2287Q1520 2290q1518 2294);"/>
                    <Edge cubics="!1404 2144(;1407,2150 1415,2153 1427,2152q1404 2144Q1409 2153q1427 2152);"/>
                    <Edge cubics="!1507 2226(;1509,2228 1510,2231 1511,2234q1507 2226Q1510 2229q1511 2234);"/>
                    <Edge cubics="!1165 2017(;1176,2020 1185,2021 1194,2019q1165 2017Q1181 2022q1194 2019);"/>
                    <Edge cubics="!1122 2006(;1137,2009 1151,2013 1165,2017q1122 2006Q1144 2011q1165 2017);"/>
                    <Edge cubics="!1119 2006(;1120,2006 1121,2006 1122,2006q1119 2006Q1120 2006q1122 2006);"/>
                    <Edge cubics="!1080 1998(;1093,2001 1106,2003 1119,2006q1080 1998Q1100 2002q1119 2006);"/>
                    <Edge cubics="!1071 1999(;1074,1998 1077,1998 1080,1998q1071 1999Q1075 1998q1080 1998);"/>
                    <Edge cubics="!1050 2002(;1059,2002 1066,2001 1071,1999q1050 2002Q1063 2002q1071 1999);"/>
                    <Edge cubics="!1040 2002(;1043,2002 1047,2002 1050,2002q1040 2002Q1045 2002q1050 2002);"/>
                    <Edge cubics="!921 1995(;924,1993 927,1992 930,1992q921 1995Q925 1992q930 1992);"/>
                    <Edge cubics="!930 1992(;967,1995 1003,1998 1040,2002q930 1992Q985 1996q1040 2002);"/>
                    <Edge cubics="!1194 2019(;1202,2018 1210,2019 1218,2020q1194 2019Q1206 2018q1218 2020);"/>
                    <Edge cubics="!779 1996(;781,1997 783,1998 784,1999q779 1996Q782 1998q784 1999);"/>
                    <Edge cubics="!650 3780(;649,3780 647,3780 646,3781q650 3780Q648 3780q646 3781);"/>
                    <Edge cubics="!656 3851(;647,3852 640,3851 637,3848q656 3851Q642 3852q637 3848);"/>
                    <Edge cubics="!665 3850(;662,3851 659,3851 656,3851q665 3850Q660 3851q656 3851);"/>
                    <Edge cubics="!646 3781(;632,3781 616,3775 597,3763q646 3781Q625 3781q597 3763);"/>
                    <Edge cubics="!921 1995(;873,1986 827,1987 784,1999q921 1995Q849 1981q784 1999);"/>
                    <Edge cubics="!732 1963(;746,1976 762,1987 779,1996q732 1963Q753 1982q779 1996);"/>
                    <Edge cubics="!1591 2010(;1522,1977 1475,1951 1451,1930q1591 2010Q1487 1961q1451 1930);"/>
                    <Edge cubics="!1676 2045(;1654,2037 1629,2027 1601,2015q1676 2045Q1643 2033q1601 2015);"/>
                    <Edge cubics="!1676 2045(;1655,2090 1633,2124 1610,2147q1676 2045Q1644 2112q1610 2147);"/>
                    <Edge cubics="!1482 2638(;1482,2643 1475,2660 1475,2678q1482 2638Q1482 2639q1479 2653Q1475 2667q1475 2678);"/>
                    <Edge cubics="!1475 2678(;1475,2681 1463,2752 1453,2752q1475 2678Q1463 2752q1453 2752);"/>
                    <Edge cubics="!1453 2752(;1442,2752 1441,2744 1441,2743q1453 2752Q1441 2752q1441 2743);"/>
                    <Edge cubics="!1441 2743(;1441,2742 1448,2663 1448,2659q1441 2743 1448 2659);"/>
                    <Edge cubics="!1448 2659(;1448,2575 1482,2631 1482,2638q1448 2659Q1448 2606q1465 2614Q1482 2623q1482 2638);"/>
                    <Edge cubics="!1457 2800(;1469,2798 1471,2810 1471,2813q1457 2800Q1471 2798q1471 2813);"/>
                    <Edge cubics="!1471 2813(;1471,2870 1386,3091 1381,3106q1471 2813Q1471 2870q1381 3106);"/>
                    <Edge cubics="!1381 3106(;1362,3156 1342,3202 1324,3254q1381 3106Q1362 3156q1324 3254);"/>
                    <Edge cubics="!1324 3254(;1311,3290 1283,3396 1272,3396q1324 3254Q1318 3272q1297 3339Q1279 3396q1272 3396);"/>
                    <Edge cubics="!1272 3396(;1270,3396 1253,3368 1253,3368q1272 3396Q1270 3396q1253 3368);"/>
                    <Edge cubics="!1253 3368(;1253,3322 1288,3284 1288,3261q1253 3368Q1253 3342q1271 3306Q1288 3270q1288 3261);"/>
                    <Edge cubics="!1288 3261(;1288,3247 1314,3149 1323,3131q1288 3261Q1288 3250q1302 3198Q1316 3144q1323 3131);"/>
                    <Edge cubics="!1323 3131(;1343,3088 1379,3050 1387,3006q1323 3131Q1328 3120q1360 3069Q1382 3032q1387 3006);"/>
                    <Edge cubics="!1387 3006(;1394,2962 1403,2920 1415,2876q1387 3006Q1397 2940q1415 2876);"/>
                    <Edge cubics="!1415 2876(;1423,2846 1446,2727 1457,2800q1415 2876Q1427 2824q1435 2799Q1450 2754q1457 2800);"/>
                  </edges>
                </DOMShape>
              </elements>
            </DOMFrame>
          </frames>
        </DOMLayer>
      </layers>
    </DOMTimeline>
  </timeline>
</DOMSymbolItem>